manifast/__init__.py
manifast/import_pkg.py
manifast/gui_utils/__init__.py
manifast/gui_utils/counter.py
manifast/gui_utils/summarize.py
manifast/iostream/__init__.py
manifast/iostream/envstream.py
manifast/iostream/filestream.py
manifast/iostream/imagestream.py
manifast/iostream/logstream.py
manifast/iostream/pdstream.py
manifast/iostream/pltstream.py
manifast/iostream/processsing.py
manifast/label_utils/__init__.py
manifast/label_utils/classify/__init__.py
manifast/label_utils/classify/gen_split_data.py
manifast/label_utils/detect/__init__.py
manifast/label_utils/detect/convert_label.py
manifast/label_utils/detect/gen_split_data.py
manifast/label_utils/detect/vis_label.py
manifast/label_utils/segment/__init__.py
manifast/label_utils/segment/colorize_mask.py
manifast/label_utils/segment/convert_label.py
manifast/label_utils/segment/convert_utils.py
manifast/label_utils/segment/gen_split_data.py
manifast/label_utils/segment/get_mask_shapes.py
manifast/label_utils/segment/vis_label.py
manifast/label_utils/segment/vis_utils.py
manifast/model_utils/__init__.py
manifast/model_utils/eval_runtime.py
manifast/model_utils/grad_cam.py
manifast/model_utils/summary.py
manifast-1.0.1.dist-info/METADATA
manifast-1.0.1.dist-info/WHEEL
manifast-1.0.1.dist-info/top_level.txt
manifast-1.0.1.dist-info/RECORD
